napari_toothfairy_annotator/FDI_Annotator.py
napari_toothfairy_annotator/__init__.py
napari_toothfairy_annotator/_reader.py
napari_toothfairy_annotator/_widget.py
napari_toothfairy_annotator/_writer.py
napari_toothfairy_annotator/napari.yaml
napari_toothfairy_annotator/_tests/__init__.py
napari_toothfairy_annotator/_tests/test_reader.py
napari_toothfairy_annotator/_tests/test_widget.py
napari_toothfairy_annotator/_tests/test_writer.py
napari_toothfairy_annotator-0.0.18.dist-info/licenses/LICENSE
napari_toothfairy_annotator-0.0.18.dist-info/METADATA
napari_toothfairy_annotator-0.0.18.dist-info/WHEEL
napari_toothfairy_annotator-0.0.18.dist-info/entry_points.txt
napari_toothfairy_annotator-0.0.18.dist-info/top_level.txt
napari_toothfairy_annotator-0.0.18.dist-info/RECORD
