Metadata-Version: 2.4
Name: napari-toothfairy-annotator
Version: 0.0.18
Summary: The plugin employed to annotate volumes employed in the ToothFairy Challenges
Home-page: https://github.com/LucaLumetti/napari-toothfairy-annotator
Author: Luca Lumetti
Author-email: lumetti.luca@gmail.com
License: MIT
Project-URL: Bug Tracker, https://github.com/LucaLumetti/napari-toothfairy-annotator/issues
Project-URL: Documentation, https://github.com/LucaLumetti/napari-toothfairy-annotator#README.md
Project-URL: Source Code, https://github.com/LucaLumetti/napari-toothfairy-annotator
Project-URL: User Support, https://github.com/LucaLumetti/napari-toothfairy-annotator/issues
Classifier: Development Status :: 2 - Pre-Alpha
Classifier: Framework :: napari
Classifier: Intended Audience :: Developers
Classifier: License :: OSI Approved :: MIT License
Classifier: Operating System :: OS Independent
Classifier: Programming Language :: Python
Classifier: Programming Language :: Python :: 3
Classifier: Programming Language :: Python :: 3 :: Only
Classifier: Programming Language :: Python :: 3.8
Classifier: Programming Language :: Python :: 3.9
Classifier: Programming Language :: Python :: 3.10
Classifier: Topic :: Scientific/Engineering :: Image Processing
Requires-Python: >=3.8
License-File: LICENSE
Requires-Dist: numpy
Requires-Dist: magicgui
Requires-Dist: qtpy
Requires-Dist: scikit-image
Provides-Extra: testing
Requires-Dist: tox; extra == "testing"
Requires-Dist: pytest; extra == "testing"
Requires-Dist: pytest-cov; extra == "testing"
Requires-Dist: pytest-qt; extra == "testing"
Requires-Dist: napari; extra == "testing"
Requires-Dist: pyqt5; extra == "testing"
Dynamic: license-file
